DeepFilterLib-0.5.5.dist-info/METADATA
DeepFilterLib-0.5.5.dist-info/WHEEL
DeepFilterLib-0.5.5.dist-info/license_files/LICENSE
DeepFilterLib-0.5.5.dist-info/license_files/LICENSE-APACHE
DeepFilterLib-0.5.5.dist-info/license_files/LICENSE-MIT
libdf/__init__.py
libdf/__init__.pyi
libdf/py.typed
libdf/libdf.cpython-38-darwin.so
DeepFilterLib-0.5.5.dist-info/RECORD
