Metadata-Version: 2.1
Name: DeepFilterLib
Version: 0.5.5
Classifier: Programming Language :: Rust
Requires-Dist: numpy >=1.22
License-File: LICENSE
License-File: LICENSE-APACHE
License-File: LICENSE-MIT
Author: Hendrik Schröter
Requires-Python: >=3.8
